langchain_plantuml/__init__.py
langchain_plantuml/diagram.py
langchain_plantuml/core/__init__.py
langchain_plantuml/core/plantuml_callback_handler.py
langchain_plantuml/plantuml/__init__.py
langchain_plantuml/plantuml/plantuml_activity_diagram_beta_callback_handler.py
langchain_plantuml/plantuml/plantuml_sequence_diagram_callback_handler.py
langchain_plantuml-0.0.7.dist-info/LICENSE
langchain_plantuml-0.0.7.dist-info/WHEEL
langchain_plantuml-0.0.7.dist-info/METADATA
langchain_plantuml-0.0.7.dist-info/RECORD
