Metadata-Version: 2.1
Name: langchain-plantuml
Version: 0.0.7
Summary: Subscribe to events using a callback and store them in PlantUML format. You can easily subscribe to events and keep them in a form that is easy to visualize and analyze.
Author-email: Lei Zhang <zhanglei@apache.org>
Requires-Python: >=3.8
Requires-Dist: langchain>=0.0.228
Requires-Dist: flake8==5.0.4 ; extra == "lint"
Requires-Dist: pyproject-flake8==5.0.4 ; extra == "lint"
Requires-Dist: isort>=5,<6 ; extra == "lint"
Requires-Dist: black>=23,<24 ; extra == "lint"
Requires-Dist: flit==3.9.0 ; extra == "package"
Requires-Dist: openai==0.27.8 ; extra == "test"
Requires-Dist: chromadb==0.3.26 ; extra == "test"
Requires-Dist: tiktoken==0.4.0 ; extra == "test"
Requires-Dist: coverage==7.2.7 ; extra == "test"
Project-URL: Documentation, https://pypi.org/project/langchain-plantuml
Project-URL: Source, https://github.com/coolbeevip/langchain_plantuml
Project-URL: Tracker, https://github.com/coolbeevip/langchain_plantuml/issues
Provides-Extra: lint
Provides-Extra: package
Provides-Extra: test
